Metadata-Version: 2.1
Name: blee.csPlayer
Version: 0.1
Summary: Blee-ICM-Plaer: A Blee (ByStar Libre-Halaal Emacs Environmen) ICM (Interactive Command Modules) Player. Takes an ICM as input and allows for its command-line execution through a rich
Home-page: http://www.by-star.net/PLPC/180047
Download-URL: http://www.by-star.net/PLPC/180047
Author: Mohsen Banan
Author-email: libre@mohsen.1.banan.byname.net
Maintainer: Mohsen Banan
Maintainer-email: libre@mohsen.1.banan.byname.net
License: AGPL
Platform: UNKNOWN
Classifier: Development Status :: 5 - Production/Stable
Classifier: Intended Audience :: Developers
Classifier: License :: OSI Approved :: GNU Affero General Public License v3
Classifier: Operating System :: POSIX
Classifier: Programming Language :: Python
Classifier: Topic :: Software Development :: Libraries
Classifier: Topic :: Software Development :: Libraries :: Python Modules
